{
    "products": [
    {
      "name": "Straight Leg Crop",
      "price": 105,
      "inventory": 120,
      "unitOfPackage": "pairs",
      "description": "Brown, causal wear",
      "image": "images/straight-leg-crop.jpg"
    },
    {
      "name": "Pants",
      "description": "Good for beach",
      "price": 105,
      "inventory": 120,
      "image": "images/pants.jpg",
      "unitOfPackage": "pairs"
    },
    {
      "name": "Limited Wear",
      "description": "Pilot",
      "price": 100,
      "inventory": 120,
      "image": "images/straight-leg-crop.jpg",
      "unitOfPackage": "pairs"
    }
    ]
}